clickpaas_toolkit/__init__.py
clickpaas_toolkit/conn/__init__.py
clickpaas_toolkit/conn/conn.py
clickpaas_toolkit/datastore/__init__.py
clickpaas_toolkit/datastore/datastore.py
clickpaas_toolkit/datastore/factory.py
clickpaas_toolkit/datastore/model.py
clickpaas_toolkit/http/__init__.py
clickpaas_toolkit/http/client.py
clickpaas_toolkit/http/error.py
clickpaas_toolkit/http/helper.py
clickpaas_toolkit/log/__init__.py
clickpaas_toolkit/utils/__init__.py
clickpaas_toolkit/utils/cipher.py
clickpaas_toolkit/utils/decorators.py
clickpaas_toolkit/utils/extend.py
clickpaas_toolkit/utils/util.py
clickpaas_toolkit-0.0.4.dist-info/METADATA
clickpaas_toolkit-0.0.4.dist-info/WHEEL
clickpaas_toolkit-0.0.4.dist-info/top_level.txt
clickpaas_toolkit-0.0.4.dist-info/RECORD
