Metadata-Version: 2.1
Name: clickpaas-toolkit
Version: 0.0.4
Summary: API Test Framework Toolkit
Home-page: http://gitlab.autotest.clickpaas.tech/qa/clickpaas-toolkit
Author: yangzhixiang
License: MIT
Classifier: Development Status :: 5 - Production/Stable
Classifier: Environment :: Web Environment
Classifier: Intended Audience :: Developers
Classifier: License :: OSI Approved :: MIT License
Classifier: Programming Language :: Python :: 3 :: Only
Classifier: Topic :: Software Development :: Libraries :: Python Modules
Requires-Dist: simplejson ==3.16.0
Requires-Dist: python-json-logger ==0.1.9
Requires-Dist: requests ==2.28.0
Requires-Dist: pymongo ==3.6.1
Requires-Dist: pymysql ==0.9.1
Requires-Dist: redis ==2.10.6
Requires-Dist: pycryptodomex ==3.12.0
